runcon/__init__.py
runcon/attrdict.py
runcon/runcon.py
runcon/scripts.py
runcon/transforms.py
runcon/utils.py
runcon/yaml_adapter.py
runcon-1.1.11.dist-info/LICENSE
runcon-1.1.11.dist-info/METADATA
runcon-1.1.11.dist-info/WHEEL
runcon-1.1.11.dist-info/entry_points.txt
runcon-1.1.11.dist-info/top_level.txt
runcon-1.1.11.dist-info/RECORD
